AppleMusicMP3/__init__.py
AppleMusicMP3/main.py
AppleMusicMP3-0.1.2.dist-info/METADATA
AppleMusicMP3-0.1.2.dist-info/WHEEL
AppleMusicMP3-0.1.2.dist-info/entry_points.txt
AppleMusicMP3-0.1.2.dist-info/top_level.txt
AppleMusicMP3-0.1.2.dist-info/RECORD
