Metadata-Version: 2.1
Name: AppleMusicMP3
Version: 0.1.2
Summary: Convert Apple Music songs to MP3.
Home-page: https://github.com/afriedsam/AppleMusicMP3
Author: Aidan Friedsam
Classifier: Programming Language :: Python :: 3
Classifier: License :: OSI Approved :: MIT License
Classifier: Operating System :: OS Independent
Requires-Python: >=3.7
Requires-Dist: requests
Requires-Dist: beautifulsoup4
Requires-Dist: lxml
Requires-Dist: yt-dlp
Requires-Dist: tqdm
Requires-Dist: pyfiglet
